ringoffive.v
`timescale 1ns / 1ps

module ringoffive (gout, ctrl);
    output [1:5] gout;
    input ctrl;
    nand #10 g1 (gout[1], ctrl, gout[5]);
    not #10 g2 (gout[2], gout[1]);
    not #10 g3 (gout[3], gout[2]);
    not #10 g4 (gout[4], gout[3]);
    not #10 g5 (gout[5], gout[4]);

endmodule

tbringoffive.v
`timescale 1ns / 1ps

module tbringoffive;
    
    wire [1:5] gout;
    reg ctrl;

   
    ringoffive uut (
        .gout(gout),
        .ctrl(ctrl)
    );

    initial begin
        
        $dumpfile("waveform.vcd");
        $dumpvars(0, tbringoffive);

        
        ctrl = 0;
        #100; 
        
        ctrl = 1;
        #500;
        
        $display("Simulation complete.");
        $finish;
    end
endmodule

waveform.vcd
$date
	Sat Mar 21 03:31:59 2026
$end
$version
	Icarus Verilog
$end
$timescale
	1ps
$end
$scope module tbringoffive $end
$var wire 5 ! gout [1:5] $end
$var reg 1 " ctrl $end
$scope module uut $end
$var wire 1 " ctrl $end
$var wire 5 # gout [1:5] $end
$upscope $end
$upscope $end
$enddefinitions $end
$comment Show the parameter values. $end
$dumpall
$end
#0
$dumpvars
bx #
0"
bx !
$end
#10000
b1xxxx !
b1xxxx #
#20000
b10xxx !
b10xxx #
#30000
b101xx !
b101xx #
#40000
b1010x !
b1010x #
#50000
b10101 !
b10101 #
#100000
1"
#110000
b101 !
b101 #
#120000
b1101 !
b1101 #
#130000
b1001 !
b1001 #
#140000
b1011 !
b1011 #
#150000
b1010 !
b1010 #
#160000
b11010 !
b11010 #
#170000
b10010 !
b10010 #
#180000
b10110 !
b10110 #
#190000
b10100 !
b10100 #
#200000
b10101 !
b10101 #
#210000
b101 !
b101 #
#220000
b1101 !
b1101 #
#230000
b1001 !
b1001 #
#240000
b1011 !
b1011 #
#250000
b1010 !
b1010 #
#260000
b11010 !
b11010 #
#270000
b10010 !
b10010 #
#280000
b10110 !
b10110 #
#290000
b10100 !
b10100 #
#300000
b10101 !
b10101 #
#310000
b101 !
b101 #
#320000
b1101 !
b1101 #
#330000
b1001 !
b1001 #
#340000
b1011 !
b1011 #
#350000
b1010 !
b1010 #
#360000
b11010 !
b11010 #
#370000
b10010 !
b10010 #
#380000
b10110 !
b10110 #
#390000
b10100 !
b10100 #
#400000
b10101 !
b10101 #
#410000
b101 !
b101 #
#420000
b1101 !
b1101 #
#430000
b1001 !
b1001 #
#440000
b1011 !
b1011 #
#450000
b1010 !
b1010 #
#460000
b11010 !
b11010 #
#470000
b10010 !
b10010 #
#480000
b10110 !
b10110 #
#490000
b10100 !
b10100 #
#500000
b10101 !
b10101 #
#510000
b101 !
b101 #
#520000
b1101 !
b1101 #
#530000
b1001 !
b1001 #
#540000
b1011 !
b1011 #
#550000
b1010 !
b1010 #
#560000
b11010 !
b11010 #
#570000
b10010 !
b10010 #
#580000
b10110 !
b10110 #
#590000
b10100 !
b10100 #
#600000
b10101 !
b10101 #
